server/__init__.py
server/server.py
server/common/__init__.py
server/common/decors.py
server/common/descripts.py
server/common/errors.py
server/common/metaclasses.py
server/common/utils.py
server/common/variables.py
server/logs/__init__.py
server/logs/client_logs/__init__.py
server/logs/configs/__init__.py
server/logs/configs/client_log_config.py
server/logs/configs/server_log_config.py
server/logs/server_logs/__init__.py
server/server_pack/__init__.py
server/server_pack/add_user.py
server/server_pack/config_window.py
server/server_pack/core.py
server/server_pack/database.py
server/server_pack/main_window.py
server/server_pack/remove_user.py
server/server_pack/stat_window.py
server/unit_test/__init__.py
server/unit_test/test_client.py
server/unit_test/test_server.py
server/unit_test/test_utils.py
my_py_mess_server-0.0.2.dist-info/METADATA
my_py_mess_server-0.0.2.dist-info/WHEEL
my_py_mess_server-0.0.2.dist-info/top_level.txt
my_py_mess_server-0.0.2.dist-info/RECORD
