Metadata-Version: 2.1
Name: my-py-mess-server
Version: 0.0.2
Summary: my_py_mess_server
Home-page: UNKNOWN
Author: Pavel Chetverikov
Author-email: kas62-96@mail.ru
License: UNKNOWN
Platform: UNKNOWN
Requires-Dist: PyQt5
Requires-Dist: PyQt5-tools
Requires-Dist: sqlalchemy
Requires-Dist: pycryptodome
